graph2edits/canonicalize_prod.py
graph2edits/eval-1.py
graph2edits/eval.py
graph2edits/prepare_data.py
graph2edits/preprocess.py
graph2edits/train.py
graph2edits/models/__init__.py
graph2edits/models/beam_search.py
graph2edits/models/encoder.py
graph2edits/models/graph2edits.py
graph2edits/models/model_utils.py
graph2edits/utils/__init__.py
graph2edits/utils/chem.py
graph2edits/utils/collate_fn.py
graph2edits/utils/datasets.py
graph2edits/utils/generate_edits.py
graph2edits/utils/mol_features.py
graph2edits/utils/reaction_actions.py
graph2edits/utils/rxn_graphs.py
syntheseus_graph2edits-0.2.0.dist-info/LICENSE
syntheseus_graph2edits-0.2.0.dist-info/METADATA
syntheseus_graph2edits-0.2.0.dist-info/WHEEL
syntheseus_graph2edits-0.2.0.dist-info/top_level.txt
syntheseus_graph2edits-0.2.0.dist-info/RECORD
